Metadata-Version: 2.1
Name: fidx
Version: 1.0.0
Summary: Float and custom indexes in Python
Home-page: UNKNOWN
Author: Davide Peressoni
Author-email: dpdmancul+fidx@gmail.com
License: MIT
Project-URL: Source, https://gitlab.com/DPDmancul/fidx
Project-URL: Tracker, https://gitlab.com/DPDmancul/fidx/-/issues
Project-URL: Documentation, https://gitlab.com/DPDmancul/fidx/-/wikis/home
Platform: UNKNOWN
Classifier: License :: OSI Approved :: MIT License
Classifier: Programming Language :: Python :: 3
Classifier: Programming Language :: Python :: 3.8
Provides-Extra: NumPy support
